selfbotpy/__init__.py
selfbotpy/languages/en.json
selfbotpy/languages/ja.json
selfbotpy/languages/thai.json
selfbotpy-1.3.6.data/data/en.json
selfbotpy-1.3.6.data/data/ja.json
selfbotpy-1.3.6.data/data/thai.json
selfbotpy-1.3.6.dist-info/LICENSE
selfbotpy-1.3.6.dist-info/METADATA
selfbotpy-1.3.6.dist-info/WHEEL
selfbotpy-1.3.6.dist-info/entry_points.txt
selfbotpy-1.3.6.dist-info/top_level.txt
selfbotpy-1.3.6.dist-info/RECORD
