Metadata-Version: 2.1
Name: selfbotpy
Version: 1.3.6
Summary: Package For selfbotpy
Home-page: UNKNOWN
Author: gummy.simps
Author-email: gummyloo909@gmail.com
License: MIT
Platform: UNKNOWN
Classifier: License :: OSI Approved :: Apache Software License
Classifier: Programming Language :: Python :: 3
Classifier: Programming Language :: Python :: 3.7
License-File: LICENSE
Requires-Dist: requests
